nebpy/__init__.py
nebpy/account.py
nebpy/transaction.py
nebpy-0.1.dist-info/METADATA
nebpy-0.1.dist-info/RECORD
nebpy-0.1.dist-info/WHEEL
nebpy-0.1.dist-info/top_level.txt
