Metadata-Version: 2.1
Name: nebpy
Version: 0.1
Summary: neb.py is the Nebulas compatible Python API
Home-page: https://github.com/xess777/neb.py
Author: Andrew Andreev
Author-email: master@fordina.com
License: LGPL
Platform: UNKNOWN
